DFF/dff.v
//==============================================================
// D Flip-Flop (Positive-edge triggered, with async reset)
//==============================================================
module dff (
    input  wire clk,     // clock
    input  wire rst_n,   // active-low asynchronous reset
    input  wire d,       // data input
    output reg  q        // data output
);

    // sequential logic
    always @(posedge clk or negedge rst_n) begin
        if (!rst_n) 
            q <= 1'b0;   // reset state
        else 
            q <= d;      // capture data on rising clock edge
    end

endmodule

tb_dff.v
module tb_dff;
    reg clk, rst_n, d;
    wire q;

    // instantiate DFF
    dff uut (
        .clk(clk),
        .rst_n(rst_n),
        .d(d),
        .q(q)
    );

    // clock generation (10ns period)
    always #5 clk = ~clk;

    initial begin
        $dumpfile("dff.vcd");  // for GTKWave
        $dumpvars(0, tb_dff);

        // init
        clk = 0; d = 0; rst_n = 0;

        // release reset after 10ns
        #12 rst_n = 1;

        // drive some values
        #10 d = 1;
        #10 d = 0;
        #10 d = 1;

        #50 $finish;
    end
endmodule

DFF/dff.vcd
$date
	Thu Oct  2 22:31:47 2025
$end
$version
	Icarus Verilog
$end
$timescale
	1s
$end
$scope module tb_dff $end
$var wire 1 ! q $end
$var reg 1 " clk $end
$var reg 1 # d $end
$var reg 1 $ rst_n $end
$scope module uut $end
$var wire 1 " clk $end
$var wire 1 # d $end
$var wire 1 $ rst_n $end
$var reg 1 ! q $end
$upscope $end
$upscope $end
$enddefinitions $end
$comment Show the parameter values. $end
$dumpall
$end
#0
$dumpvars
0$
0#
0"
0!
$end
#5
1"
#10
0"
#12
1$
#15
1"
#20
0"
#22
1#
#25
1!
1"
#30
0"
#32
0#
#35
0!
1"
#40
0"
#42
1#
#45
1!
1"
