ALU/alu.v
// alu.v - Simple 8-bit ALU
module alu (
    input  [7:0] a, b,       // operands
    input  [2:0] op,         // operation select
    output reg [7:0] result  // result
);

always @(*) begin
    case(op)
        3'b000: result = a + b;       // ADD
        3'b001: result = a - b;       // SUB
        3'b010: result = a & b;       // AND
        3'b011: result = a | b;       // OR
        3'b100: result = a ^ b;       // XOR
        3'b101: result = a << 1;      // Shift Left
        3'b110: result = a >> 1;      // Shift Right
        3'b111: result = ~a;          // NOT
        default: result = 8'b0;
    endcase
end

endmodule

tb_alu.v
//==============================================================
// Testbench for 8-bit ALU (matches your module ports)
//==============================================================
`timescale 1ns/1ps

module tb_alu;
    reg [7:0] a, b;
    reg [2:0] op;
    wire [7:0] result;

    // Instantiate ALU (matches your module exactly)
    alu uut (
        .a(a),
        .b(b),
        .op(op),
        .result(result)
    );

    initial begin
        $dumpfile("alu.vcd");
        $dumpvars(0, tb_alu);

        // Test patterns
        a = 8'h0A; b = 8'h03; op = 3'b000; #10; // ADD
        a = 8'h0A; b = 8'h03; op = 3'b001; #10; // SUB
        a = 8'h0A; b = 8'h03; op = 3'b010; #10; // AND
        a = 8'h0A; b = 8'h03; op = 3'b011; #10; // OR
        a = 8'h0A; b = 8'h03; op = 3'b100; #10; // XOR
        a = 8'h0A; b = 8'h03; op = 3'b101; #10; // NAND
        a = 8'h0A; b = 8'h0F; op = 3'b110; #10; // SLT
        a = 8'h0A; b = 8'h03; op = 3'b111; #10; // NOP

        #20 $finish;
    end
endmodule

ALU/alu.vcd
$date
	Sat Oct 04 13:54:48 2025
$end
$version
	Icarus Verilog
$end
$timescale
	1ps
$end
$scope module tb_alu $end
$var wire 8 ! result [7:0] $end
$var reg 8 " a [7:0] $end
$var reg 8 # b [7:0] $end
$var reg 3 $ op [2:0] $end
$scope module uut $end
$var wire 8 % a [7:0] $end
$var wire 8 & b [7:0] $end
$var wire 3 ' op [2:0] $end
$var reg 8 ( result [7:0] $end
$upscope $end
$upscope $end
$enddefinitions $end
#0
$dumpvars
b1101 (
b0 '
b11 &
b1010 %
b0 $
b11 #
b1010 "
b1101 !
$end
#10000
b111 !
b111 (
b1 $
b1 '
#20000
b10 !
b10 (
b10 $
b10 '
#30000
b1011 !
b1011 (
b11 $
b11 '
#40000
b1001 !
b1001 (
b100 $
b100 '
#50000
b10100 !
b10100 (
b101 $
b101 '
#60000
b101 !
b101 (
b110 $
b110 '
b1111 #
b1111 &
#70000
b11110101 !
b11110101 (
b111 $
b111 '
b11 #
b11 &
